rainbow/__init__.py
rainbow/rainbow_console.py
rainbow_console-0.0.1.dist-info/LICENSE
rainbow_console-0.0.1.dist-info/METADATA
rainbow_console-0.0.1.dist-info/WHEEL
rainbow_console-0.0.1.dist-info/top_level.txt
rainbow_console-0.0.1.dist-info/RECORD
