Metadata-Version: 2.1
Name: rainbow-console
Version: 0.0.1
Summary: This module is designed to color the information displayed in the console.
Home-page: https://github.com/Elysiumskrieger/rainbow-console
Author: Elysiumskrieger
Author-email: kurt@i-e.space
License: UNKNOWN
Platform: UNKNOWN
Classifier: Programming Language :: Python :: 3.8
Classifier: License :: OSI Approved :: Apache Software License
Classifier: Operating System :: OS Independent
Requires-Python: >=3.5
